llm_lucid_memory-0.2.1.dist-info/licenses/LICENSE
lucid_memory/__init__.py
lucid_memory/chain_engine.py
lucid_memory/chunker.py
lucid_memory/digestor.py
lucid_memory/gui.py
lucid_memory/memory_graph.py
lucid_memory/memory_node.py
lucid_memory/processor.py
lucid_memory/proxy_server.py
lucid_memory/retriever.py
llm_lucid_memory-0.2.1.dist-info/METADATA
llm_lucid_memory-0.2.1.dist-info/WHEEL
llm_lucid_memory-0.2.1.dist-info/entry_points.txt
llm_lucid_memory-0.2.1.dist-info/top_level.txt
llm_lucid_memory-0.2.1.dist-info/RECORD
