Metadata-Version: 2.4
Name: llm-lucid-memory
Version: 0.2.1
Summary: Lucid Memory - Modular reasoning brain for small LLMs
Home-page: https://github.com/benschneider/llm-lucid-memory
Author: Ben Schneider
Author-email: benh.schneider@gmail.com
Project-URL: Source, https://github.com/benschneider/llm-lucid-memory
Project-URL: Issue Tracker, https://github.com/benschneider/llm-lucid-memory/issues
Classifier: Programming Language :: Python :: 3
Classifier: License :: OSI Approved :: Apache Software License
Classifier: Operating System :: OS Independent
Classifier: Intended Audience :: Developers
Classifier: Topic :: Scientific/Engineering :: Artificial Intelligence
Requires-Python: >=3.8
License-File: LICENSE
Requires-Dist: fastapi
Requires-Dist: uvicorn
Requires-Dist: requests
Dynamic: author
Dynamic: author-email
Dynamic: classifier
Dynamic: description
Dynamic: description-content-type
Dynamic: home-page
Dynamic: license-file
Dynamic: project-url
Dynamic: requires-dist
Dynamic: requires-python
Dynamic: summary
